{"chunk_definitions":[{"chunk_id":"csetup_chunk","chunk_label":"setup","document_id":"790DBFE7","expansion_state":0,"options":{"engine":"r","include":false,"label":"setup"},"row":7,"row_count":1,"visible":true},{"chunk_id":"ceg6fkahdz15p","chunk_label":"unnamed-chunk-1","document_id":"790DBFE7","expansion_state":0,"options":{"engine":"r","label":"unnamed-chunk-162"},"row":45,"row_count":1,"visible":true},{"chunk_id":"cr28mpkje0esn","chunk_label":"unnamed-chunk-2","document_id":"790DBFE7","expansion_state":0,"options":{"engine":"r","label":"unnamed-chunk-171"},"row":54,"row_count":1,"visible":true},{"chunk_id":"cr5skviglw1kq","chunk_label":"unnamed-chunk-4","document_id":"790DBFE7","expansion_state":0,"options":{"engine":"r","label":"unnamed-chunk-165"},"row":74,"row_count":1,"visible":true},{"chunk_id":"cq2rv71dyn633","chunk_label":"unnamed-chunk-5","document_id":"790DBFE7","expansion_state":0,"options":{"engine":"r","label":"unnamed-chunk-164"},"row":91,"row_count":1,"visible":true},{"chunk_id":"cpvz3b33y7vmw","chunk_label":"unnamed-chunk-6","document_id":"790DBFE7","expansion_state":0,"options":{"engine":"r","include":false,"label":"unnamed-chunk-87"},"row":267,"row_count":1,"visible":true}],"chunk_rendered_width":442,"default_chunk_options":{"echo":true},"doc_write_time":1618807138,"working_dir":null}